buildtools/build.py
m3_cli-4.158.3.data/data/m3cli/access_meta.json
m3_cli-4.158.3.data/data/m3cli/bash_m3cli_complete.sh
m3_cli-4.158.3.data/data/m3cli/commands_def.json
m3_cli-4.158.3.data/data/m3cli/m3cli_complete.py
m3_cli-4.158.3.data/data/m3cli/zsh_m3cli_complete.sh
m3_cli-4.158.3.dist-info/licenses/LICENSE
m3cli/__init__.py
m3cli/commands_def.json
m3cli/commands_help.py
m3cli/m3.py
m3cli/connections/__init__.py
m3cli/connections/rabbitmq_connection.py
m3cli/customizer/customizer.py
m3cli/docs/__init__.py
m3cli/docs/cli_to_docx.py
m3cli/docs/cli_to_md.py
m3cli/docs/usage_docx.py
m3cli/docs/commons/__init__.py
m3cli/docs/commons/commands_table.py
m3cli/docs/commons/m3_preprocessor.py
m3cli/docs/commons/title_page_docx.py
m3cli/docs/md_to_docx/__init__.py
m3cli/docs/md_to_docx/custom_styles.py
m3cli/m3cli_complete/__init__.py
m3cli/m3cli_complete/access_meta.json
m3cli/m3cli_complete/autocomplete_setup.py
m3cli/m3cli_complete/bash_m3cli_complete.sh
m3cli/m3cli_complete/m3cli_complete.py
m3cli/m3cli_complete/zsh_m3cli_complete.sh
m3cli/models/__init__.py
m3cli/models/interactive_parameter.py
m3cli/plugins/__init__.py
m3cli/plugins/activate-platform-service.py
m3cli/plugins/activate-vlan.py
m3cli/plugins/add-schedule-instances.py
m3cli/plugins/add-service-section.py
m3cli/plugins/apply-terraform-template.py
m3cli/plugins/aws-management-console.py
m3cli/plugins/azure-management-console.py
m3cli/plugins/backup.py
m3cli/plugins/billing-region-types.py
m3cli/plugins/budgets-report.py
m3cli/plugins/cost-object-report.py
m3cli/plugins/cost-usage-report.py
m3cli/plugins/create-image.py
m3cli/plugins/create-instance-quota.py
m3cli/plugins/create-key.py
m3cli/plugins/create-recommendation-settings.py
m3cli/plugins/create-schedule.py
m3cli/plugins/create-storage-quota.py
m3cli/plugins/deactivate-platform-service.py
m3cli/plugins/deactivate-vlan.py
m3cli/plugins/decrypt-password.py
m3cli/plugins/delete-schedule-instances.py
m3cli/plugins/delete-scripts.py
m3cli/plugins/delete-service-section.py
m3_cli-4.158.3.dist-info/METADATA
m3_cli-4.158.3.dist-info/WHEEL
m3_cli-4.158.3.dist-info/entry_points.txt
m3_cli-4.158.3.dist-info/top_level.txt
m3_cli-4.158.3.dist-info/RECORD
