Metadata-Version: 2.4
Name: m3-cli
Version: 4.158.3
Summary: The Maestro3 Command Line Interface (CLI) is a unified tool to manage your Maestro services and resources
Author-email: maestrocloudcontrol <support@maestrocontrol.cloud>
Project-URL: Homepage, https://github.com/Maestro-Cloud-Control/m3-cli
Keywords: Maestro3,Command Line Interface,CLI,CLOUD
License-File: LICENSE
Requires-Dist: setuptools==68.2.1
Requires-Dist: click==7.1.2
Requires-Dist: requests==2.31.0
Requires-Dist: tabulate==0.9.0
Requires-Dist: pika==1.0.0b1
Requires-Dist: cryptography==41.0.3
Requires-Dist: jsonschema==3.2.0
Requires-Dist: pyyaml==6.0.1
Requires-Dist: Pillow==10.0.0
Requires-Dist: packaging==25.0
Requires-Dist: beautifulsoup4==4.10.0
Dynamic: license-file
